{
  "$schema": "https://wails.io/schemas/config.v2.json",
  "name": "ADBKit",
  "outputfilename": "ADBKit",
  "frontend:install": "pnpm install",
  "frontend:build": "pnpm build",
  "frontend:dev:watcher": "pnpm dev",
  "frontend:dev:serverUrl": "http://localhost:4333",
  "frontend:dev:message": "ready in",
  "author": {
    "name": "Drenzzz",
    "email": "realdrenzzz@gmail.com"
  },
  "info": {
    "companyName": "Drenzzz",
    "productName": "ADBKit",
    "productVersion": "1.1.0",
    "fileVersion": "1.1.0",
    "copyright": "Copyright (c) 2025 Drenzzz",
    "comments": ""
  }
}
